pyxcel/__init__.py
pyxcel/__version__.py
pyxcel/api.py
pyxcel/billing.py
pyxcel/client.py
pyxcel/const.py
pyxcel/exceptions.py
pyxcel/overview.py
pyxcel/usages.py
pyxcel-1.2.1.dist-info/DESCRIPTION.rst
pyxcel-1.2.1.dist-info/METADATA
pyxcel-1.2.1.dist-info/RECORD
pyxcel-1.2.1.dist-info/WHEEL
pyxcel-1.2.1.dist-info/metadata.json
pyxcel-1.2.1.dist-info/top_level.txt
tests/fixtures/__init__.py
tests/fixtures/billing.py
tests/fixtures/general.py
tests/fixtures/overview.py
tests/fixtures/usages.py
